lizahwlibbiglove/__init__.py
lizahwlibbiglove/ast_graph.py
lizahwlibbiglove/fibonacci.py
lizahwlibbiglove/main.py
lizahwlibbiglove-0.0.1.dist-info/METADATA
lizahwlibbiglove-0.0.1.dist-info/WHEEL
lizahwlibbiglove-0.0.1.dist-info/top_level.txt
lizahwlibbiglove-0.0.1.dist-info/RECORD
